errsole/__init__.py
errsole/main.py
errsole_sdk-0.0.1.dist-info/LICENSE
errsole_sdk-0.0.1.dist-info/METADATA
errsole_sdk-0.0.1.dist-info/WHEEL
errsole_sdk-0.0.1.dist-info/top_level.txt
errsole_sdk-0.0.1.dist-info/RECORD
