Metadata-Version: 2.1
Name: errsole-sdk
Version: 0.0.1
Summary: Logger and Debugger
Home-page: https://github.com/errsole/errsole-python
Author: Rishi Meena
Author-email: rishi@errsole.com
Project-URL: Bug Tracker, https://github.com/errsole/errsole-python/issues
Classifier: Programming Language :: Python :: 3
Classifier: License :: OSI Approved :: MIT License
Classifier: Operating System :: OS Independent
Requires-Python: >=3.0
License-File: LICENSE
